transformer_components_michaelkosmider/__init__.py
transformer_components_michaelkosmider/functions.py
transformer_components_michaelkosmider/multi_head_attention.py
transformer_components_michaelkosmider/sublayers.py
transformer_components_michaelkosmider/transformer_decoder.py
transformer_components_michaelkosmider/transformer_encoder.py
transformer_components_michaelkosmider/transformer_encoder_decoder.py
transformer_components_michaelkosmider-0.1.1.dist-info/licenses/LICENSE
transformer_components_michaelkosmider-0.1.1.dist-info/METADATA
transformer_components_michaelkosmider-0.1.1.dist-info/WHEEL
transformer_components_michaelkosmider-0.1.1.dist-info/top_level.txt
transformer_components_michaelkosmider-0.1.1.dist-info/RECORD
