Metadata-Version: 2.4
Name: transformer_components_michaelkosmider
Version: 0.1.1
Summary: Reusable Transformer model components.
Author-email: Michael Kosmider <michael.kosmider24@gmail.com>
License-Expression: MIT
Requires-Python: >=3.8
License-File: LICENSE
Dynamic: license-file
